tree_sitter_zeek/__init__.pyi
tree_sitter_zeek/binding.c
tree_sitter_zeek/__init__.py
tree_sitter_zeek/py.typed
tree_sitter_zeek/_binding.abi3.so
tree_sitter_zeek/queries/highlights.scm
tree_sitter_zeek-0.2.11.dist-info/RECORD
tree_sitter_zeek-0.2.11.dist-info/WHEEL
tree_sitter_zeek-0.2.11.dist-info/top_level.txt
tree_sitter_zeek-0.2.11.dist-info/METADATA
tree_sitter_zeek-0.2.11.dist-info/licenses/LICENSE
