Metadata-Version: 2.4
Name: tree-sitter-zeek
Version: 0.2.11
Summary: Zeek grammar for tree-sitter
License: BSD-3-Clause
Project-URL: Homepage, https://github.com/zeek/tree-sitter-zeek
Keywords: incremental,parsing,tree-sitter,zeek
Classifier: Intended Audience :: Developers
Classifier: License :: OSI Approved :: BSD License
Classifier: Topic :: Software Development :: Compilers
Classifier: Topic :: Text Processing :: Linguistic
Classifier: Typing :: Typed
Requires-Python: >=3.10
License-File: LICENSE
Provides-Extra: core
Requires-Dist: tree-sitter~=0.23; extra == "core"
Dynamic: license-file
